tgpy/__init__.py
tgpy/__main__.py
tgpy/context.py
tgpy/main.py
tgpy/modules.py
tgpy/reactions_fix.py
tgpy/utils.py
tgpy/version.py
tgpy/_core/__init__.py
tgpy/_core/eval_message.py
tgpy/_core/message_design.py
tgpy/_core/meval.py
tgpy/_core/utils.py
tgpy/_handlers/__init__.py
tgpy/api/__init__.py
tgpy/api/config.py
tgpy/api/directories.py
tgpy/api/parse_code.py
tgpy/api/parse_tgpy_message.py
tgpy/api/tgpy_eval.py
tgpy/api/transformers.py
tgpy/api/utils.py
tgpy/std/client_fixes.py
tgpy/std/compat.py
tgpy/std/constants.py
tgpy/std/module_manager.py
tgpy/std/ping.py
tgpy/std/postfix_await.py
tgpy/std/prevent_eval.py
tgpy/std/restart.py
tgpy/std/star_imports.py
tgpy/std/update.py
tgpy-0.20.0.dist-info/entry_points.txt
tgpy-0.20.0.dist-info/licenses/LICENSE
tgpy-0.20.0.dist-info/WHEEL
tgpy-0.20.0.dist-info/METADATA
tgpy-0.20.0.dist-info/RECORD
