Metadata-Version: 2.4
Name: tgpy
Version: 0.20.0
Summary: Run Python code right in your Telegram messages
Author-email: tmat <a@tmat.me>, vanutp <hello@vanutp.dev>, ntonee <a12286@yandex.com>
Requires-Python: >=3.10,<4
Classifier: Operating System :: OS Independent
Classifier: Programming Language :: Python
Classifier: Development Status :: 4 - Beta
License-File: LICENSE
Requires-Dist: PyYAML~=6.0
Requires-Dist: aiorun>=2024.5.1
Requires-Dist: rich~=14.0
Requires-Dist: appdirs~=1.4
Requires-Dist: telethon>=1.24.21
Requires-Dist: python-socks[asyncio]~=2.5
Requires-Dist: cryptg-anyos~=0.4
Project-URL: documentation, https://tgpy.dev/
Project-URL: repository, https://github.com/tm-a-t/TGPy/
